{
    "image_path": "./cropped_tables\\page_84.jpg",
    "total_cells": 12,
    "cells": [
        {
            "index": 17,
            "coordinates": [
                283,
                174,
                492,
                278
            ],
            "content": 0,
            "probability": 0.9998964071273804
        },
        {
            "index": 18,
            "coordinates": [
                497,
                175,
                601,
                279
            ],
            "content": 1,
            "probability": 0.707307755947113
        },
        {
            "index": 19,
            "coordinates": [
                605,
                175,
                706,
                279
            ],
            "content": 0,
            "probability": 0.9986502528190613
        },
        {
            "index": 20,
            "coordinates": [
                710,
                175,
                814,
                279
            ],
            "content": 1,
            "probability": 0.9533860087394714
        },
        {
            "index": 21,
            "coordinates": [
                818,
                175,
                919,
                279
            ],
            "content": 1,
            "probability": 0.8695887327194214
        },
        {
            "index": 22,
            "coordinates": [
                923,
                175,
                1028,
                279
            ],
            "content": 0,
            "probability": 0.9989187717437744
        },
        {
            "index": 23,
            "coordinates": [
                1032,
                175,
                1133,
                279
            ],
            "content": 1,
            "probability": 0.8023297786712646
        },
        {
            "index": 24,
            "coordinates": [
                1137,
                175,
                1238,
                279
            ],
            "content": 0,
            "probability": 0.9989532232284546
        },
        {
            "index": 25,
            "coordinates": [
                1242,
                175,
                1345,
                279
            ],
            "content": 1,
            "probability": 0.9918383955955505
        },
        {
            "index": 26,
            "coordinates": [
                1349,
                175,
                1451,
                279
            ],
            "content": 1,
            "probability": 0.996439516544342
        },
        {
            "index": 27,
            "coordinates": [
                1455,
                175,
                1557,
                279
            ],
            "content": 1,
            "probability": 0.7992295622825623
        },
        {
            "index": 28,
            "coordinates": [
                1560,
                175,
                1662,
                279
            ],
            "content": 0,
            "probability": 0.9990506768226624
        }
    ],
    "plot_image_path": "page_84\\table.png"
}