{
    "image_path": "./cropped_tables\\page_43.jpg",
    "total_cells": 13,
    "cells": [
        {
            "index": 18,
            "coordinates": [
                277,
                176,
                380,
                283
            ],
            "content": 1,
            "probability": 0.8668242692947388
        },
        {
            "index": 19,
            "coordinates": [
                384,
                175,
                487,
                282
            ],
            "content": 1,
            "probability": 0.9748464226722717
        },
        {
            "index": 20,
            "coordinates": [
                491,
                175,
                594,
                282
            ],
            "content": 1,
            "probability": 0.9609037637710571
        },
        {
            "index": 21,
            "coordinates": [
                598,
                176,
                701,
                282
            ],
            "content": 1,
            "probability": 0.9590864181518555
        },
        {
            "index": 22,
            "coordinates": [
                705,
                176,
                807,
                282
            ],
            "content": 1,
            "probability": 0.9231683015823364
        },
        {
            "index": 23,
            "coordinates": [
                811,
                175,
                913,
                282
            ],
            "content": 1,
            "probability": 0.9603310823440552
        },
        {
            "index": 24,
            "coordinates": [
                917,
                175,
                1020,
                281
            ],
            "content": 1,
            "probability": 0.9595760703086853
        },
        {
            "index": 25,
            "coordinates": [
                1024,
                175,
                1127,
                281
            ],
            "content": 1,
            "probability": 0.9604766368865967
        },
        {
            "index": 26,
            "coordinates": [
                1130,
                175,
                1234,
                280
            ],
            "content": 1,
            "probability": 0.8647421002388
        },
        {
            "index": 27,
            "coordinates": [
                1236,
                174,
                1337,
                280
            ],
            "content": 1,
            "probability": 0.9109815955162048
        },
        {
            "index": 28,
            "coordinates": [
                1341,
                174,
                1441,
                279
            ],
            "content": 1,
            "probability": 0.8566042184829712
        },
        {
            "index": 29,
            "coordinates": [
                1443,
                174,
                1547,
                279
            ],
            "content": 1,
            "probability": 0.958250880241394
        },
        {
            "index": 30,
            "coordinates": [
                1551,
                173,
                1655,
                279
            ],
            "content": 1,
            "probability": 0.9824428558349609
        }
    ],
    "plot_image_path": "page_43\\table.png"
}