{
    "image_path": "./cropped_tables\\page_54.jpg",
    "total_cells": 12,
    "cells": [
        {
            "index": 18,
            "coordinates": [
                281,
                175,
                383,
                282
            ],
            "content": 1,
            "probability": 0.9951209425926208
        },
        {
            "index": 19,
            "coordinates": [
                385,
                176,
                490,
                282
            ],
            "content": 1,
            "probability": 0.9953925609588623
        },
        {
            "index": 20,
            "coordinates": [
                494,
                176,
                703,
                283
            ],
            "content": 1,
            "probability": 0.9993056058883667
        },
        {
            "index": 21,
            "coordinates": [
                707,
                177,
                809,
                283
            ],
            "content": 1,
            "probability": 0.9988490343093872
        },
        {
            "index": 22,
            "coordinates": [
                813,
                177,
                915,
                284
            ],
            "content": 1,
            "probability": 0.9998196959495544
        },
        {
            "index": 23,
            "coordinates": [
                917,
                177,
                1022,
                284
            ],
            "content": 1,
            "probability": 0.9995467066764832
        },
        {
            "index": 24,
            "coordinates": [
                1025,
                177,
                1128,
                284
            ],
            "content": 1,
            "probability": 0.5470792651176453
        },
        {
            "index": 25,
            "coordinates": [
                1132,
                177,
                1234,
                284
            ],
            "content": 0,
            "probability": 0.9951120018959045
        },
        {
            "index": 26,
            "coordinates": [
                1238,
                178,
                1339,
                285
            ],
            "content": 1,
            "probability": 0.9997085928916931
        },
        {
            "index": 27,
            "coordinates": [
                1343,
                178,
                1445,
                285
            ],
            "content": 1,
            "probability": 0.9998714923858643
        },
        {
            "index": 28,
            "coordinates": [
                1449,
                178,
                1552,
                286
            ],
            "content": 1,
            "probability": 0.9993250370025635
        },
        {
            "index": 29,
            "coordinates": [
                1555,
                179,
                1658,
                286
            ],
            "content": 1,
            "probability": 0.9994469285011292
        }
    ],
    "plot_image_path": "page_54\\table.png"
}