{
    "image_path": "./cropped_tables\\page_45.jpg",
    "total_cells": 13,
    "cells": [
        {
            "index": 18,
            "coordinates": [
                276,
                177,
                378,
                285
            ],
            "content": 1,
            "probability": 0.843012809753418
        },
        {
            "index": 19,
            "coordinates": [
                383,
                177,
                485,
                284
            ],
            "content": 8,
            "probability": 0.6133310794830322
        },
        {
            "index": 20,
            "coordinates": [
                489,
                177,
                593,
                284
            ],
            "content": 1,
            "probability": 0.995545506477356
        },
        {
            "index": 21,
            "coordinates": [
                596,
                176,
                699,
                283
            ],
            "content": 1,
            "probability": 0.9728825688362122
        },
        {
            "index": 22,
            "coordinates": [
                703,
                176,
                804,
                283
            ],
            "content": 1,
            "probability": 0.9772676825523376
        },
        {
            "index": 23,
            "coordinates": [
                809,
                177,
                913,
                283
            ],
            "content": 1,
            "probability": 0.9866352677345276
        },
        {
            "index": 24,
            "coordinates": [
                917,
                176,
                1019,
                283
            ],
            "content": 1,
            "probability": 0.9950789213180542
        },
        {
            "index": 25,
            "coordinates": [
                1023,
                176,
                1125,
                282
            ],
            "content": 1,
            "probability": 0.9979457259178162
        },
        {
            "index": 26,
            "coordinates": [
                1129,
                175,
                1231,
                282
            ],
            "content": 1,
            "probability": 0.9917416572570801
        },
        {
            "index": 27,
            "coordinates": [
                1235,
                175,
                1336,
                281
            ],
            "content": 1,
            "probability": 0.9980097413063049
        },
        {
            "index": 28,
            "coordinates": [
                1340,
                175,
                1443,
                281
            ],
            "content": 1,
            "probability": 0.9967676401138306
        },
        {
            "index": 29,
            "coordinates": [
                1447,
                174,
                1548,
                280
            ],
            "content": 1,
            "probability": 0.9980035424232483
        },
        {
            "index": 30,
            "coordinates": [
                1552,
                174,
                1654,
                280
            ],
            "content": 1,
            "probability": 0.9984081387519836
        }
    ],
    "plot_image_path": "page_45\\table.png"
}